Metadata-Version: 1.0
Name: xlazypipka
Version: 0.0.1
Summary: New pipka
Home-page: UNKNOWN
Author: Egor
Author-email: aerobatics7@gmail.com
License: UNKNOWN
Platform: UNKNOWN
